CHANGES.rst
LICENSE
MANIFEST.in
README.rst
setup.py
django_iban/__init__.py
django_iban/fields.py
django_iban/forms.py
django_iban/models.py
django_iban/sepa_countries.py
django_iban/tests.py
django_iban/validators.py
django_iban.egg-info/PKG-INFO
django_iban.egg-info/SOURCES.txt
django_iban.egg-info/dependency_links.txt
django_iban.egg-info/not-zip-safe
django_iban.egg-info/requires.txt
django_iban.egg-info/top_level.txt
django_iban/locale/bg/LC_MESSAGES/django.mo
django_iban/locale/bg/LC_MESSAGES/django.po
django_iban/locale/de/LC_MESSAGES/django.mo
django_iban/locale/de/LC_MESSAGES/django.po
django_iban/locale/es/LC_MESSAGES/django.mo
django_iban/locale/es/LC_MESSAGES/django.po
django_iban/locale/fr/LC_MESSAGES/django.mo
django_iban/locale/fr/LC_MESSAGES/django.po
django_iban/locale/nl/LC_MESSAGES/django.mo
django_iban/locale/nl/LC_MESSAGES/django.po
django_iban/locale/pl/LC_MESSAGES/django.mo
django_iban/locale/pl/LC_MESSAGES/django.po